{
  "data": [
    {
      "id": "root",
      "name": "地图组件"
    },
    {
      "id": "examples",
      "name": "通用示例",
      "parent": "root"
    },
    {
      "id": "example_api_",
      "name": "初始化地图",
      "parent": "examples",
      "href": "cw/examples/sandbox/sandbox.html?example=api_basemap_create",
      "iframe": true
    },
    {
      "id": "example_api_basemap_edit",
      "name": "设置地图中心",
      "parent": "examples",
      "href": "cw/examples/sandbox/sandbox.html?example=api_basemap_edit",
      "iframe": true
    },
    {
      "id": "example_api_markers_init",
      "name": "初始化标记",
      "parent": "examples",
      "href": "cw/examples/sandbox/sandbox.html?example=api_markers_init",
      "iframe": true
    },
    {
      "id": "example_api_markers_on",
      "name": "绑定标记事件",
      "parent": "examples",
      "href": "cw/examples/sandbox/sandbox.html?example=api_markers_on",
      "iframe": true
    },
    {
      "id": "example_api_markers_data",
      "name": "绑定标记数据",
      "parent": "examples",
      "href": "cw/examples/sandbox/sandbox.html?example=api_markers_data",
      "iframe": true
    },
    {
      "id": "example_api_menu_bind",
      "name": "绑定菜单信息",
      "parent": "examples",
      "href": "cw/examples/sandbox/sandbox.html?example=api_menu_bind",
      "iframe": true
    },
    {
      "id": "example_api_dialogs_info_window",
      "name": "消息提示",
      "parent": "examples",
      "href": "cw/examples/sandbox/sandbox.html?example=api_dialogs_info_window",
      "iframe": true
    },
    {
      "id": "example-4",
      "name": "查询轨迹数据",
      "parent": "examples",
      "href": "cw/examples/sandbox/sandbox.html?example=api_directions_query",
      "iframe": true
    },
    {
      "id": "example-9",
      "name": "获取经纬度坐标",
      "parent": "examples",
      "href": "cw/examples/sandbox/sandbox.html?example=api_util_lonat",
      "iframe": true
    },
   {
      "id": "example-10",
      "name": "初始化覆盖物图层",
      "parent": "examples",
      "href": "cw/examples/sandbox/sandbox.html?example=api_polygon_init",
      "iframe": true
    },
    {
      "id": "example-12",
      "name": "增删覆盖物",
      "parent": "examples",
      "href": "cw/examples/sandbox/sandbox.html?example=api_polygon_add",
      "iframe": true
    },
    {
      "id": "example-11",
      "name": "编辑覆盖物",
      "parent": "examples",
      "href": "cw/examples/sandbox/sandbox.html?example=api_polygon_edit",
      "iframe": true
    },
    {
      "id": "example_api_widgets_map_type",
      "name": "地图切换控件",
      "parent": "examples",
      "href": "cw/examples/sandbox/sandbox.html?example=api_widgets_map_type",
      "iframe": true
    },
    {
      "id": "exampleapi_widgets_select_toolbar",
      "name": "地图选择控件",
      "parent": "examples",
      "href": "cw/examples/sandbox/sandbox.html?example=api_widgets_select_toolbar",
      "iframe": true
    },
    {
      "id": "arcgis",
      "name": "ArcGIS 示例",
      "parent": "root"
    },
    {
      "id": "arcgis-1",
      "name": "上下文菜单",
      "parent": "arcgis",
      "href": "cw/examples/arcgis-1-contextmenu.html",
      "iframe": true
    },
    {
      "id": "quanzhou",
      "name": "泉州示例",
      "parent": "root"
    },
    {
      "id": "quanzhou-1",
      "name": "摄像头信息",
      "parent": "quanzhou",
      "href": "cw/examples/cw-quanzhou-camera.html",
      "iframe": true
    },
    {
      "id": "quanzhou-2",
      "name": "区域信息",
      "parent": "quanzhou",
      "href": "cw/examples/cw-quanzhou-regions.html",
      "iframe": true
    },
    {
      "id": "quanzhou-3",
      "name": "路径信息",
      "parent": "quanzhou",
      "href": "cw/examples/cw-quanzhou-directions.html",
      "iframe": true
    },
    {
      "id": "quanzhou-4",
      "name": "地图类型控件",
      "parent": "quanzhou",
      "href": "cw/examples/cw-quanzhou-map-type.html",
      "iframe": true
    }
  ]
}
